pillow_affine/__about__.py
pillow_affine/__init__.py
pillow_affine/matrix.py
pillow_affine/transforms.py
pillow_affine/utils.py
pillow_affine-0.1.dist-info/LICENSE
pillow_affine-0.1.dist-info/METADATA
pillow_affine-0.1.dist-info/WHEEL
pillow_affine-0.1.dist-info/top_level.txt
pillow_affine-0.1.dist-info/RECORD
